parametro/__init__.py
parametro/__main__.py
parametro/file_export.py
parametro/file_import.py
parametro/file_utils.py
parametro-0.1.0.dist-info/LICENSE.txt
parametro-0.1.0.dist-info/METADATA
parametro-0.1.0.dist-info/WHEEL
parametro-0.1.0.dist-info/entry_points.txt
parametro-0.1.0.dist-info/top_level.txt
parametro-0.1.0.dist-info/RECORD
