Metadata-Version: 2.1
Name: parametro
Version: 0.1.0
Author: Nicolas Byl
Author-email: nicolas.byl@nexineer.io
Requires-Python: >=3.8
License-File: LICENSE.txt
Requires-Dist: boto3
Requires-Dist: click
